bandl/__init__.py
bandl/angel_broking.py
bandl/binance.py
bandl/coinbase.py
bandl/common.py
bandl/exception.py
bandl/five_paisa.py
bandl/helper.py
bandl/nasdaq.py
bandl/nse_data.py
bandl/nse_urls.py
bandl/request.py
bandl/samco.py
bandl/yfinance.py
bandl-0.1.0.dist-info/LICENSE
bandl-0.1.0.dist-info/METADATA
bandl-0.1.0.dist-info/WHEEL
bandl-0.1.0.dist-info/top_level.txt
bandl-0.1.0.dist-info/RECORD
