Metadata-Version: 2.1
Name: bandl
Version: 0.1.0
Summary: Utilities for the analysis of financial data
Home-page: UNKNOWN
Author: stolgo Developers
Author-email: stockalgos@gmail.com
License: MIT
Download-URL: https://github.com/stockalgo/bandl/archive/v0.1.0.tar.gz
Project-URL: Organization, http://www.bandl.io
Project-URL: Source, https://github.com/stockalgo/bandl
Project-URL: Tracker, https://github.com/stockalgo/bandl/issues
Keywords: python,yahoo-finance-api,coinbase-api,nse,binance-api,coinbase-pro,5paisa,nasdaq-crawler,yfinance,5paisa-trading-apis,nasdaq-python-api,yfinance-api,nasqad,samco,nse-python-api,optionchain,angelbroking-apis,binance-python-api,coinbase-python-api,samco-python-api
Platform: UNKNOWN
Classifier: Development Status :: 5 - Production/Stable
Classifier: Intended Audience :: Developers
Classifier: Topic :: Software Development :: Build Tools
Classifier: License :: OSI Approved :: MIT License
Classifier: Programming Language :: Python :: 3
Classifier: Programming Language :: Python :: 3.5
Classifier: Programming Language :: Python :: 3.6
Classifier: Programming Language :: Python :: 3.7
Classifier: Programming Language :: Python :: 3.8
Requires-Dist: requests
Requires-Dist: pandas
Requires-Dist: datetime
Requires-Dist: openpyxl
Requires-Dist: futures
Requires-Dist: beautifulsoup4
Requires-Dist: lxml
